iar_inflector/__init__.py
iar_inflector/acep_consts.py
iar_inflector/acepcion.py
iar_inflector/entr_consts.py
iar_inflector/entrada.py
iar_inflector/flex_consts.py
iar_inflector/flexionador.py
iar_inflector/forma.py
iar_inflector/lema.py
iar_inflector/parseador_rae.py
iar_inflector/parseador_rae_consts.py
iar_inflector/parseador_wikci.py
iar_inflector/parseador_wikci_consts.py
iar_inflector-1.2.3.dist-info/METADATA
iar_inflector-1.2.3.dist-info/WHEEL
iar_inflector-1.2.3.dist-info/top_level.txt
iar_inflector-1.2.3.dist-info/RECORD
